{
  "_fv": 73,
  "_type": "structure",
  "definition": {
    "structure": "blazesmith_house",
    "projection": "rigid",
    "ignoredBlocks": [
      {
        "value": "Blocks.STRUCTURE_BLOCK"
      },
      {
        "value": "Blocks.AIR"
      },
      {
        "value": "Blocks.GRASS"
      },
      {
        "value": "Blocks.SPRUCE_TRAPDOOR"
      },
      {
        "value": "Blocks.BARRIER"
      }
    ],
    "spacing": 40,
    "separation": 10,
    "restrictionBiomes": [
      {
        "value": "taiga"
      },
      {
        "value": "extreme_hills_with_trees"
      }
    ],
    "terrainAdaptation": "beard_thin",
    "generationStep": "SURFACE_STRUCTURES",
    "surfaceDetectionType": "WORLD_SURFACE_WG",
    "useStartHeight": false,
    "startHeightProviderType": "UNIFORM",
    "startHeightMin": 0,
    "startHeightMax": 128,
    "size": 1,
    "maxDistanceFromCenter": 64,
    "jigsawPools": []
  }
}