{
  "_fv": 73,
  "_type": "gui",
  "definition": {
    "type": 1,
    "width": 176,
    "height": 166,
    "inventoryOffsetX": 0,
    "inventoryOffsetY": 0,
    "renderBgLayer": true,
    "doesPauseGame": false,
    "components": [
      {
        "type": "label",
        "data": {
          "name": "label_workshop_of_the_infernal_flame",
          "text": {
            "fixedValue": "Recipe Boook"
          },
          "color": {
            "value": -12829636,
            "falpha": 0.0
          },
          "x": 132,
          "y": 43,
          "locked": false
        }
      },
      {
        "type": "label",
        "data": {
          "name": "label_invintory",
          "text": {
            "fixedValue": "Invintory"
          },
          "color": {
            "value": -12829636,
            "falpha": 0.0
          },
          "x": 132,
          "y": 108,
          "locked": false
        }
      },
      {
        "type": "outputslot",
        "data": {
          "id": 0,
          "disablePickup": {
            "fixedValue": true
          },
          "dropItemsWhenNotBound": false,
          "x": 259,
          "y": 74,
          "locked": false
        }
      },
      {
        "type": "inputslot",
        "data": {
          "inputLimit": {
            "value": ""
          },
          "disablePlacement": {
            "fixedValue": true
          },
          "id": 1,
          "disablePickup": {
            "fixedValue": true
          },
          "dropItemsWhenNotBound": false,
          "x": 151,
          "y": 74,
          "locked": false
        }
      },
      {
        "type": "inputslot",
        "data": {
          "inputLimit": {
            "value": ""
          },
          "disablePlacement": {
            "fixedValue": true
          },
          "id": 2,
          "disablePickup": {
            "fixedValue": true
          },
          "dropItemsWhenNotBound": false,
          "x": 169,
          "y": 74,
          "locked": false
        }
      },
      {
        "type": "inputslot",
        "data": {
          "inputLimit": {
            "value": ""
          },
          "disablePlacement": {
            "fixedValue": true
          },
          "id": 3,
          "disablePickup": {
            "fixedValue": true
          },
          "dropItemsWhenNotBound": false,
          "x": 187,
          "y": 74,
          "locked": false
        }
      },
      {
        "type": "button",
        "data": {
          "name": "button_empty",
          "text": ">",
          "isUndecorated": false,
          "width": 30,
          "height": 20,
          "x": 263,
          "y": 45,
          "locked": false
        }
      },
      {
        "type": "button",
        "data": {
          "name": "button_empty1",
          "text": "<",
          "isUndecorated": false,
          "width": 30,
          "height": 20,
          "x": 229,
          "y": 45,
          "locked": false
        }
      }
    ],
    "onTick": {
      "name": "Craft"
    },
    "gridSettings": {
      "sx": 18,
      "sy": 18,
      "ox": 11,
      "oy": 15,
      "snapOnGrid": false
    }
  }
}